README.rst
setup.py
dhub/__init__.py
dhub/config.json
dhub/config.py
dhub/dataset.py
dhub/datasets.py
dhub/dhubrc.py
dhub/element.py
dhub.egg-info/PKG-INFO
dhub.egg-info/SOURCES.txt
dhub.egg-info/dependency_links.txt
dhub.egg-info/not-zip-safe
dhub.egg-info/requires.txt
dhub.egg-info/top_level.txt
dhub/interpreters/__init__.py
dhub/interpreters/bin_image.py
dhub/interpreters/bin_text.py
dhub/interpreters/interpreter.py
dhub/tests/__init__.py
dhub/tests/interpreters/__init__.py
dhub/tests/interpreters/test_bin_text.py
dhub/wrapper/__init__.py
dhub/wrapper/api_wrapper.py
dhub/wrapper/smart_updater.py