Metadata-Version: 1.1
Name: dhub
Version: 0.0.6
Summary: ML Data Hub client for managing datasets of MlDataHub from Python3.
Home-page: http://github.com/ipazc/dhub
Author: Iván de Paz Centeno
Author-email: ipazc@unileon.es
License: GNU GPLv3 or later
Keywords: machine-learning mldatahub data hub datasets dataset store client
Platform: UNKNOWN
Classifier: Development Status :: 1 - Planning
Classifier: Environment :: Console
Classifier: Intended Audience :: Developers
Classifier: Intended Audience :: Education
Classifier: Intended Audience :: Science/Research
Classifier: Natural Language :: English
Classifier: Operating System :: POSIX :: Linux
Classifier: Programming Language :: Python :: 3.4
Classifier: Programming Language :: Python :: 3.5
Classifier: Programming Language :: Python :: 3.6
Classifier: Programming Language :: Python :: 3.7
Classifier: Framework :: Flask
Classifier: License :: OSI Approved :: GNU General Public License v3 or later (GPLv3+)
